Workbook

Sheet Dashboard
A1: Berkeley Event Value Twin
A2: Kite Festival prototype — complete value, not only permit cost. Select scenario on Controls sheet.
B4: Active scenario | C4: =Controls!B5 -> Central
B6: City net fiscal impact | E6: Net direct local spending | H6: Total economic output
B7: ='City Fiscal'!B23 -> 45747.636 | E7: ='Visitor Economics'!B18 -> 723593.52 | H7: ='Visitor Economics'!B21 -> 1027502.8
B11: Realized attendance | E11: Vehicle arrivals | H11: Transportation emissions
B12: ='Visitor Economics'!B5 -> 32200 | E12: ='Mobility & Emissions'!B8 -> 8318.3333 | H12: ='Mobility & Emissions'!B21 -> 93.3317
B16: City cost recovery | E16: Public-value score | H16: Parking surplus / (shortfall)
B17: ='City Fiscal'!B25 -> 1.4158876 | E17: ='Public Value'!D14 -> 70.2 | H17: ='Mobility & Emissions'!B16 -> -3989.2
A21: Interpretation
B22: =IF('City Fiscal'!B23>=0,"The active scenario is estimated to cover incremental City cost while also producing local economic and public-value effects.","The active scenario requires an estimated City subsidy. Compare that subsidy with incremental local economic activity, public value, mobility impacts, and uncertainty before making a policy judgment.") -> The active scenario is estimated to cover incremental City cost while also producing local economic and public-value effects.
B27: Metric | C27: Value
B28: City revenue | C28: ='City Fiscal'!B10 -> 155747.64
B29: City cost | C29: ='City Fiscal'!B13 -> 110000
B30: Net direct spending | C30: ='Visitor Economics'!B18 -> 723593.52
B31: Total output | C31: ='Visitor Economics'!B21 -> 1027502.8
A35: Uncertainty summary
B36: Expected fiscal impact | C36: ='Monte Carlo'!B1008 -> 32811.389
B37: P10 fiscal impact | C37: ='Monte Carlo'!B1009 -> 15878.261
B38: Median fiscal impact | C38: ='Monte Carlo'!B1010 -> 32882.523
B39: P90 fiscal impact | C39: ='Monte Carlo'!B1011 -> 49137.871
B40: Probability of break-even | C40: ='Monte Carlo'!B1012 -> 0.998

Sheet Controls
A1: Berkeley Event Value Twin — Controls
A2: Blue cells are editable. Values in v1 are illustrative placeholders until Berkeley records and survey data are loaded.
A4: Scenario selection
A5: Active scenario | B5: Central | D5: Choose Conservative, Central, or High
A8: Assumption | B8: Conservative | C8: Central | D8: High | E8: Unit | F8: Status / source
A9: Total attendance | B9: 25000 | C9: 35000 | D9: 45000 | E9: people | F9: Illustrative; replace with event counts
A10: Berkeley resident share | B10: 0.45 | C10: 0.35 | D10: 0.25 | E10: % | F10: Survey / ZIP code
A11: Festival-attributed share: nonresidents | B11: 0.65 | C11: 0.78 | D11: 0.88 | E11: % | F11: Intercept survey
A12: Festival-attributed share: residents | B12: 0.05 | C12: 0.12 | D12: 0.2 | E12: % | F12: Intercept survey
A13: Avg Berkeley spend: resident attendee | B13: 18 | C13: 25 | D13: 34 | E13: $/person | F13: Intercept survey
A14: Avg Berkeley spend: nonresident day visitor | B14: 35 | C14: 52 | D14: 72 | E14: $/person | F14: Intercept survey
A15: Overnight visitor share of nonresidents | B15: 0.02 | C15: 0.05 | D15: 0.09 | E15: % | F15: Intercept survey
A16: Avg incremental lodging spend | B16: 145 | C16: 185 | D16: 240 | E16: $/room-night | F16: Survey / hotel data
A17: People per hotel room | B17: 1.8 | C17: 2 | D17: 2.2 | E17: people | F17: Survey
A18: Local capture of attendee spending | B18: 0.72 | C18: 0.82 | D18: 0.9 | E18: % | F18: Location of expenditure
A19: Economic output multiplier | B19: 1.25 | C19: 1.42 | D19: 1.58 | E19: x | F19: IMPLAN; RIMS II cross-check
A20: Value-added share of total output | B20: 0.48 | C20: 0.54 | D20: 0.6 | E20: % | F20: IMPLAN sector results
... A37: Displaced local spending | B37: 60000 | C37: 35000 | D37: 15000 | E37: $ | F37: Nearby business / visitor survey
A40: Active scenario values (formula-driven)
A41: Assumption | B41: Active value | C41: Unit
A42: =A9 -> Total attendance | B42: =IF($B$5="Conservative",B9,IF($B$5="High",D9,C9)) -> 35000 | C42: =E9 -> people
A43: =A10 -> Berkeley resident share | B43: =IF($B$5="Conservative",B10,IF($B$5="High",D10,C10)) -> 0.35 | C43: =E10 -> %
A44: =A11 -> Festival-attributed share: nonresidents | B44: =IF($B$5="Conservative",B11,IF($B$5="High",D11,C11)) -> 0.78 | C44: =E11 -> %
A45: =A12 -> Festival-attributed share: residents | B45: =IF($B$5="Conservative",B12,IF($B$5="High",D12,C12)) -> 0.12 | C45: =E12 -> %
A46: =A13 -> Avg Berkeley spend: resident attendee | B46: =IF($B$5="Conservative",B13,IF($B$5="High",D13,C13)) -> 25 | C46: =E13 -> $/person
A47: =A14 -> Avg Berkeley spend: nonresident day visitor | B47: =IF($B$5="Conservative",B14,IF($B$5="High",D14,C14)) -> 52 | C47: =E14 -> $/person
A48: =A15 -> Overnight visitor share of nonresidents | B48: =IF($B$5="Conservative",B15,IF($B$5="High",D15,C15)) -> 0.05 | C48: =E15 -> %
A49: =A16 -> Avg incremental lodging spend | B49: =IF($B$5="Conservative",B16,IF($B$5="High",D16,C16)) -> 185 | C49: =E16 -> $/room-night
A50: =A17 -> People per hotel room | B50: =IF($B$5="Conservative",B17,IF($B$5="High",D17,C17)) -> 2 | C50: =E17 -> people
A51: =A18 -> Local capture of attendee spending | B51: =IF($B$5="Conservative",B18,IF($B$5="High",D18,C18)) -> 0.82 | C51: =E18 -> %
A52: =A19 -> Economic output multiplier | B52: =IF($B$5="Conservative",B19,IF($B$5="High",D19,C19)) -> 1.42 | C52: =E19 -> x
A53: =A20 -> Value-added share of total output | B53: =IF($B$5="Conservative",B20,IF($B$5="High",D20,C20)) -> 0.54 | C53: =E20 -> %
... A70: =A37 -> Displaced local spending | B70: =IF($B$5="Conservative",B37,IF($B$5="High",D37,C37)) -> 35000 | C70: =E37 -> $

Sheet Visitor Economics
A1: Visitor Economics
A2: Incremental spending only: attribution, local capture, lodging, displacement, and multiplier effects.
A4: Attendance segmentation
A5: Realized attendance | B5: =Controls!B42*Controls!B69 -> 32200 | C5: Planned attendance × weather realization
A6: Berkeley residents | B6: =B5*Controls!B43 -> 11270
A7: Non-Berkeley attendees | B7: =B5-B6 -> 20930
A8: Incremental resident attendees | B8: =B6*Controls!B45 -> 1352.4
A9: Incremental nonresident attendees | B9: =B7*Controls!B44 -> 16325.4
A10: Overnight visitors | B10: =B7*Controls!B48 -> 1046.5
A12: Direct incremental spending
A13: Resident attendee spending | B13: =B8*Controls!B46*Controls!B51 -> 27724.2
A14: Nonresident day-visitor spending | B14: =(B9-B10)*Controls!B47*Controls!B51 -> 651492.3
A15: Incremental lodging spending | B15: =B10/Controls!B50*Controls!B49*Controls!B51 -> 79377.025
A16: Gross direct incremental spending | B16: =SUM(B13:B15) -> 758593.52
A17: Less displaced local spending | B17: =-Controls!B70 -> -35000
A18: Net direct incremental spending | B18: =SUM(B16:B17) -> 723593.52
A20: Regional economic effects
A21: Total economic output | B21: =B18*Controls!B52 -> 1027502.8
A22: Value added | B22: =B21*Controls!B53 -> 554851.51
A23: Labor income | B23: =B21*Controls!B54 -> 349350.95
A24: Indirect + induced output | B24: =B21-B18 -> 303909.28
A26: Fiscal bridge
A27: Estimated taxable incremental sales | B27: =B18*Controls!B56 -> 520987.34
A28: Estimated City sales-tax revenue | B28: =B27*Controls!B55 -> 4688.886

Sheet City Fiscal
A1: City Fiscal Impact
A2: Separates true incremental cash cost from allocated accounting cost and compares City revenues.
A4: City revenues
A5: Permit and organizer fees | B5: =Controls!B58 -> 45000
A6: Estimated sales-tax revenue | B6: ='Visitor Economics'!B28 -> 4688.886
A7: Parking vehicles | B7: ='Mobility & Emissions'!B8 -> 8318.3333
A8: Gross parking revenue | B8: =B7*Controls!B59 -> 124775
A9: City-retained parking revenue | B9: =B8*Controls!B60 -> 106058.75
A10: Total City revenue | B10: =SUM(B5:B6,B9) -> 155747.64
A12: City costs
A13: Incremental City service cost | B13: =Controls!B57 -> 110000
A14: Police / traffic | B14: =$B$13*0.35 -> 38500 | C14: 0.35
A15: Fire / EMS | B15: =$B$13*0.12 -> 13200 | C15: 0.12
A16: Public Works / sanitation | B16: =$B$13*0.18 -> 19800 | C16: 0.18
A17: Parks / Marina staff | B17: =$B$13*0.18 -> 19800 | C17: 0.18
A18: Temporary facilities / contracts | B18: =$B$13*0.12 -> 13200 | C18: 0.12
A19: Administration / permitting | B19: =$B$13*0.05 -> 5500 | C19: 0.05
A20: Allocation check | B20: =SUM(B14:B19) -> 110000 | C20: =SUM(C14:C19) -> 1
A22: Net fiscal result
A23: Net City fiscal impact | B23: =B10-B13 -> 45747.636 | C23: Positive = surplus; negative = subsidy
A24: City subsidy per attendee | B24: =IF('Visitor Economics'!B5=0,0,-MIN(B23,0)/'Visitor Economics'!B5) -> 0
A25: City cost recovery ratio | B25: =IF(B13=0,0,B10/B13) -> 1.4158876

Sheet Mobility & Emissions
A1: Mobility & Emissions
A2: Event travel, parking pressure, transportation emissions, and solid waste.
A4: Travel demand
A5: Realized attendance | B5: ='Visitor Economics'!B5 -> 32200
A6: Auto travelers | B6: =B5*Controls!B61 -> 19964
A7: Average vehicle occupancy | B7: =Controls!B62 -> 2.4
A8: Vehicle arrivals | B8: =IF(B7=0,0,B6/B7) -> 8318.3333
A9: Transit travelers | B9: =B5*Controls!B64 -> 4830
A10: Bike/walk travelers | B10: =B5*Controls!B65 -> 5474
A11: Other / unallocated travelers | B11: =MAX(0,B5-B6-B9-B10) -> 1932
A13: Parking and roadway indicators
A14: Usable event parking supply | B14: 2000 | C14: spaces | D14: Illustrative; replace with current inventory
A15: Peak parking demand | B15: =B8*0.72 -> 5989.2 | C15: Illustrative 72% peak overlap
A16: Parking surplus / (shortfall) | B16: =B14-B15 -> -3989.2
A17: Parking utilization | B17: =IF(B14=0,0,B15/B14) -> 2.9946
A19: Emissions and waste
A20: Vehicle miles traveled | B20: =B8*Controls!B63 -> 282823.33
A21: Transportation emissions | B21: =B20*Controls!B66 -> 93.3317 | C21: metric tons CO2e
A22: Total event waste | B22: =B5*Controls!B67/2000 -> 9.66 | C22: short tons
A23: Landfilled waste | B23: =B22*(1-Controls!B68) -> 3.864 | C23: short tons
A24: Diverted waste | B24: =B22*Controls!B68 -> 5.796 | C24: short tons

Sheet Public Value
A1: Public Value Scorecard
A2: Nonmarket benefits remain visible as measured outcomes instead of being forced into unsupported dollar values.
A4: Weighted scorecard
A5: Outcome | B5: Weight | C5: Score (0–100) | D5: Weighted score | E5: Evidence status | F5: Measurement instrument
A6: Free family recreation | B6: 0.18 | C6: 75 | D6: =B6*C6 -> 13.5 | E6: Illustrative | F6: Attendee survey / observation
A7: Accessibility and inclusion | B7: 0.14 | C7: 65 | D7: =B7*C7 -> 9.1 | E7: Illustrative | F7: Accessibility audit + survey
A8: Youth engagement | B8: 0.12 | C8: 70 | D8: =B8*C8 -> 8.4 | E8: Illustrative | F8: Program counts + survey
A9: Berkeley identity / visibility | B9: 0.14 | C9: 80 | D9: =B9*C9 -> 11.2 | E9: Illustrative | F9: Media analytics + resident survey
A10: Waterfront activation | B10: 0.12 | C10: 78 | D10: =B10*C10 -> 9.36 | E10: Illustrative | F10: Footfall / dwell time
A11: Local nonprofit/vendor exposure | B11: 0.1 | C11: 68 | D11: =B11*C11 -> 6.8 | E11: Illustrative | F11: Vendor follow-up survey
A12: Resident satisfaction | B12: 0.12 | C12: 62 | D12: =B12*C12 -> 7.44 | E12: Illustrative | F12: Representative resident survey
A13: Environmental stewardship | B13: 0.08 | C13: 55 | D13: =B13*C13 -> 4.4 | E13: Illustrative | F13: Waste / habitat / travel indicators
A14: Total / composite score | B14: =SUM(B6:B13) -> 1 | D14: =SUM(D6:D13) -> 70.2
A17: Distributional checks
A18: Share of attendees from Berkeley | B18: =Controls!B43 -> 0.35 | C18: Target / survey
A19: Share using non-auto modes | B19: =Controls!B64+Controls!B65 -> 0.32 | C19: Mobility survey
A20: City subsidy per attendee | B20: ='City Fiscal'!B24 -> 0 | C20: Fiscal model
A21: Free admission | B21: 1 | C21: Event design
A22: Parking shortfall | B22: =MAX(0,-'Mobility & Emissions'!B16) -> 3989.2 | C22: Mobility model

Sheet Monte Carlo
A1: Monte Carlo Uncertainty
A2: 1,000 fixed probability draws. Rebuild draws when assumptions change materially; no volatile RAND formulas are used.
A4: Trial | B4: Attendance factor | C4: Attribution factor | D4: Spend factor | E4: Cost factor | F4: Auto-share factor | G4: Realized attendance | H4: Net direct spending | I4: Total output | J4: City revenue | K4: Net fiscal impact | L4: CO2e (t)
A5: 1 | B5: 0.94676067 | C5: 1.000979 | D5: 0.97965145 | E5: 1.1223824 | F5: 1.0319852 | G5: ='Visitor Economics'!$B$5*B5 -> 30485.693 | H5: =MAX(0,'Visitor Economics'!$B$18*B5*C5*D5) -> 671786.73 | I5: =H5*Controls!$B$52 -> 953937.16 | J5: ='City Fiscal'!$B$5+(H5*Controls!$B$56*Controls!$B$55)+('City Fiscal'!$B$9*B5*F5) -> 152977.13 | K5: =J5-('City Fiscal'!$B$13*E5) -> 29515.069 | L5: ='Mobility & Emissions'!$B$21*B5*F5 -> 91.189081
A6: 2 | B6: 0.91058331 | C6: 1.1126515 | D6: 1.0204379 | E6: 1.0435448 | F6: 1.0763624 | G6: ='Visitor Economics'!$B$5*B6 -> 29320.782 | H6: =MAX(0,'Visitor Economics'!$B$18*B6*C6*D6) -> 748100.79 | I6: =H6*Controls!$B$52 -> 1062303.1 | J6: ='City Fiscal'!$B$5+(H6*Controls!$B$56*Controls!$B$55)+('City Fiscal'!$B$9*B6*F6) -> 153797.74 | K6: =J6-('City Fiscal'!$B$13*E6) -> 39007.814 | L6: ='Mobility & Emissions'!$B$21*B6*F6 -> 91.476043
A7: 3 | B7: 0.96992006 | C7: 0.97956503 | D7: 0.93670833 | E7: 0.93982362 | F7: 1.0909449 | G7: ='Visitor Economics'!$B$5*B7 -> 31231.426 | H7: =MAX(0,'Visitor Economics'!$B$18*B7*C7*D7) -> 643973.9 | I7: =H7*Controls!$B$52 -> 914442.94 | J7: ='City Fiscal'!$B$5+(H7*Controls!$B$56*Controls!$B$55)+('City Fiscal'!$B$9*B7*F7) -> 161396.83 | K7: =J7-('City Fiscal'!$B$13*E7) -> 58016.233 | L7: ='Mobility & Emissions'!$B$21*B7*F7 -> 98.757014
A8: 4 | B8: 0.97687228 | C8: 1.0159904 | D8: 1.1491846 | E8: 0.91776963 | F8: 1.0499375 | G8: ='Visitor Economics'!$B$5*B8 -> 31455.288 | H8: =MAX(0,'Visitor Economics'!$B$18*B8*C8*D8) -> 825300 | I8: =H8*Controls!$B$52 -> 1171926 | J8: ='City Fiscal'!$B$5+(H8*Controls!$B$56*Controls!$B$55)+('City Fiscal'!$B$9*B8*F8) -> 159127.62 | K8: =J8-('City Fiscal'!$B$13*E8) -> 58172.958 | L8: ='Mobility & Emissions'!$B$21*B8*F8 -> 95.726112
A9: 5 | B9: 0.81354996 | C9: 1.0163371 | D9: 0.83332448 | E9: 0.94269597 | F9: 1.0370509 | G9: ='Visitor Economics'!$B$5*B9 -> 26196.309 | H9: =MAX(0,'Visitor Economics'!$B$18*B9*C9*D9) -> 498575.36 | I9: =H9*Controls!$B$52 -> 707977.01 | J9: ='City Fiscal'!$B$5+(H9*Controls!$B$56*Controls!$B$55)+('City Fiscal'!$B$9*B9*F9) -> 137711.76 | K9: =J9-('City Fiscal'!$B$13*E9) -> 34015.207 | L9: ='Mobility & Emissions'!$B$21*B9*F9 -> 78.743276
A10: 6 | B10: 0.90745823 | C10: 0.89029225 | D10: 1.1285659 | E10: 0.95004576 | F10: 0.9651195 | G10: ='Visitor Economics'!$B$5*B10 -> 29220.155 | H10: =MAX(0,'Visitor Economics'!$B$18*B10*C10*D10) -> 659752.15 | I10: =H10*Controls!$B$52 -> 936848.05 | J10: ='City Fiscal'!$B$5+(H10*Controls!$B$56*Controls!$B$55)+('City Fiscal'!$B$9*B10*F10) -> 142162.04 | K10: =J10-('City Fiscal'!$B$13*E10) -> 37657.011 | L10: ='Mobility & Emissions'!$B$21*B10*F10 -> 81.740429
A11: 7 | B11: 0.83359851 | C11: 1.0051349 | D11: 1.0818966 | E11: 1.1039221 | F11: 0.93007809 | G11: ='Visitor Economics'!$B$5*B11 -> 26841.872 | H11: =MAX(0,'Visitor Economics'!$B$18*B11*C11*D11) -> 655936.34 | I11: =H11*Controls!$B$52 -> 931429.61 | J11: ='City Fiscal'!$B$5+(H11*Controls!$B$56*Controls!$B$55)+('City Fiscal'!$B$9*B11*F11) -> 131479.06 | K11: =J11-('City Fiscal'!$B$13*E11) -> 10047.626 | L11: ='Mobility & Emissions'!$B$21*B11*F11 -> 72.361159
A12: 8 | B12: 0.94261783 | C12: 0.87668333 | D12: 1.0577664 | E12: 1.1236523 | F12: 0.91166441 | G12: ='Visitor Economics'!$B$5*B12 -> 30352.294 | H12: =MAX(0,'Visitor Economics'!$B$18*B12*C12*D12) -> 632503.37 | I12: =H12*Controls!$B$52 -> 898154.79 | J12: ='City Fiscal'!$B$5+(H12*Controls!$B$56*Controls!$B$55)+('City Fiscal'!$B$9*B12*F12) -> 140240.33 | K12: =J12-('City Fiscal'!$B$13*E12) -> 16638.58 | L12: ='Mobility & Emissions'!$B$21*B12*F12 -> 80.204702
A13: 9 | B13: 0.88913844 | C13: 0.92431203 | D13: 1.0547342 | E13: 1.1324681 | F13: 1.1057564 | G13: ='Visitor Economics'!$B$5*B13 -> 28630.258 | H13: =MAX(0,'Visitor Economics'!$B$18*B13*C13*D13) -> 627228.34 | I13: =H13*Controls!$B$52 -> 890664.25 | J13: ='City Fiscal'!$B$5+(H13*Controls!$B$56*Controls!$B$55)+('City Fiscal'!$B$9*B13*F13) -> 153338.27 | K13: =J13-('City Fiscal'!$B$13*E13) -> 28766.783 | L13: ='Mobility & Emissions'!$B$21*B13*F13 -> 91.760973
A14: 10 | B14: 0.91262579 | C14: 0.95155607 | D14: 1.1768819 | E14: 1.0194382 | F14: 1.0690834 | G14: ='Visitor Economics'!$B$5*B14 -> 29386.55 | H14: =MAX(0,'Visitor Economics'!$B$18*B14*C14*D14) -> 739528.12 | I14: =H14*Controls!$B$52 -> 1050129.9 | J14: ='City Fiscal'!$B$5+(H14*Controls!$B$56*Controls!$B$55)+('City Fiscal'!$B$9*B14*F14) -> 153270.81 | K14: =J14-('City Fiscal'!$B$13*E14) -> 41132.607 | L14: ='Mobility & Emissions'!$B$21*B14*F14 -> 91.061225
A15: 11 | B15: 0.858735 | C15: 0.97734993 | D15: 0.92326514 | E15: 1.0304237 | F15: 1.1148219 | G15: ='Visitor Economics'!$B$5*B15 -> 27651.267 | H15: =MAX(0,'Visitor Economics'!$B$18*B15*C15*D15) -> 560699.74 | I15: =H15*Controls!$B$52 -> 796193.63 | J15: ='City Fiscal'!$B$5+(H15*Controls!$B$56*Controls!$B$55)+('City Fiscal'!$B$9*B15*F15) -> 150167.25 | K15: =J15-('City Fiscal'!$B$13*E15) -> 36820.647 | L15: ='Mobility & Emissions'!$B$21*B15*F15 -> 89.349849
A16: 12 | B16: 0.95238343 | C16: 0.98407011 | D16: 1.0012758 | E16: 1.1333863 | F16: 0.9844154 | G16: ='Visitor Economics'!$B$5*B16 -> 30666.747 | H16: =MAX(0,'Visitor Economics'!$B$18*B16*C16*D16) -> 679025.75 | I16: =H16*Controls!$B$52 -> 964216.56 | J16: ='City Fiscal'!$B$5+(H16*Controls!$B$56*Controls!$B$55)+('City Fiscal'!$B$9*B16*F16) -> 148834.5 | K16: =J16-('City Fiscal'!$B$13*E16) -> 24162.01 | L16: ='Mobility & Emissions'!$B$21*B16*F16 -> 87.502288
... A1004: 1000 | B1004: 0.92893958 | C1004: 0.97032964 | D1004: 0.99797316 | E1004: 1.089209 | F1004: 1.0026484 | G1004: ='Visitor Economics'!$B$5*B1004 -> 29911.854 | H1004: =MAX(0,'Visitor Economics'!$B$18*B1004*C1004*D1004) -> 650909.03 | I1004: =H1004*Controls!$B$52 -> 924290.82 | J1004: ='City Fiscal'!$B$5+(H1004*Controls!$B$56*Controls!$B$55)+('City Fiscal'!$B$9*B1004*F1004) -> 148000.99 | K1004: =J1004-('City Fiscal'!$B$13*E1004) -> 28187.997 | L1004: ='Mobility & Emissions'!$B$21*B1004*F1004 -> 86.929123
A1007: Distribution summary
A1008: Expected net fiscal impact | B1008: =AVERAGE(K5:K1004) -> 32811.389
A1009: P10 net fiscal impact | B1009: =PERCENTILE(K5:K1004,0.1) -> 15878.261
A1010: Median net fiscal impact | B1010: =MEDIAN(K5:K1004) -> 32882.523
A1011: P90 net fiscal impact | B1011: =PERCENTILE(K5:K1004,0.9) -> 49137.871
A1012: Probability of fiscal break-even | B1012: =COUNTIF(K5:K1004,">=0")/1000 -> 0.998
A1013: Expected total economic output | B1013: =AVERAGE(I5:I1004) -> 921922.82
A1014: Expected transportation emissions | B1014: =AVERAGE(L5:L1004) -> 84.630445

Sheet Evidence Register
A1: Evidence Register
A2: Tracks whether each material input is observed, modeled, stipulated, or still missing.
A4: Domain | B4: Input / evidence | C4: Status | D4: Confidence | E4: As-of date | F4: Source / custodian | G4: URL or record request | H4: Model owner | I4: Update rule
A5: Attendance | B5: 2017–2019 hourly/daily attendance | C5: Missing | D5: Low | F5: Organizer / City special events | I5: Replace scenario range
A6: Fiscal | B6: Police and traffic marginal cost | C6: Missing | D6: Low | F6: Berkeley Police / Finance | G6: https://berkeleyca.gov/your-government/public-records | I6: Reconstruct overtime and contracts
A7: Fiscal | B7: Fire/EMS marginal cost | C7: Missing | D7: Low | F7: Berkeley Fire / Finance | G7: https://berkeleyca.gov/your-government/public-records | I7: Reconstruct event-specific cost
A8: Fiscal | B8: Marina/Parks staffing and sanitation | C8: Missing | D8: Low | F8: Parks, Recreation & Waterfront | G8: https://berkeleyca.gov/your-government/public-records | I8: Separate fixed from incremental
A9: Economy | B9: Creative Economy impact methodology | C9: Available | D9: High | E9: 2025 | F9: City of Berkeley | G9: https://berkeleyca.gov/sites/default/files/documents/Berkeley-Creative-Economy-Impact-Report.pdf | I9: Use consistent geography and outputs
A10: Economy | B10: Attendee spending by origin | C10: Missing | D10: Low | F10: Future intercept survey | G10: https://www.americansforthearts.org/by-program/reports-and-data/research-studies-publications/arts-economic-prosperity-6 | I10: Survey every pilot event
A11: Economy | B11: Regional multiplier set | C11: Modeled | D11: Medium | F11: IMPLAN + BEA RIMS II | G11: https://www.bea.gov/resources/methodologies/RIMSII-user-guide | I11: Refresh to analysis year
A12: Mobility | B12: Waterfront parking/TDM framework | C12: Available | D12: High | E12: 2025 | F12: City of Berkeley | G12: https://berkeleyca.gov/sites/default/files/documents/Berkeley-WTPF-Parking-and-TDM-Plan-March-2025-Public-Draft.pdf | I12: Update when plan changes
A13: Mobility | B13: Actual event mode share and occupancy | C13: Missing | D13: Low | F13: Future mobility survey | G13: https://highways.dot.gov/media/87306 | I13: Survey and counts
A14: Environment | B14: Event waste and diversion | C14: Missing | D14: Low | F14: Event operator / Zero Waste | I14: Weigh or audit loads
A15: Community | B15: Resident and attendee public-value measures | C15: Missing | D15: Low | F15: Representative survey | G15: https://www.americansforthearts.org/by-program/reports-and-data/research-studies-publications/arts-economic-prosperity-6 | I15: Pre/post or event survey
A16: Geospatial | B16: Open Data assets and boundaries | C16: Available | D16: High | F16: City of Berkeley | G16: https://berkeleyca.gov/your-government/public-records/open-data-portal | I16: Refresh annually

Sheet Data Requests
A1: Data Acquisition Plan
A2: Records and measurements needed to replace illustrative assumptions with Berkeley-specific evidence.
A4: Priority | B4: Request / measurement | C4: Custodian | D4: Historical period | E4: Format | F4: Reason | G4: Minimum fields | H4: Status
A5: 1 | B5: Event invoices, permits, and organizer payments | C5: Finance / PRW | D5: 2017–2019 | E5: CSV/PDF | F5: Reconstruct City fiscal ledger | G5: date, account, description, amount, payer/payee | H5: Not started
A6: 1 | B6: Event-specific staff hours and overtime | C6: Police, Fire, Public Works, PRW | D6: 2017–2019 | E6: CSV | F6: Estimate marginal service cost | G6: department, employee class, regular/overtime hours, rate | H6: Not started
A7: 1 | B7: Attendance estimates and methodology | C7: Organizer / City | D7: 2017–2019 | E7: CSV/PDF | F7: Anchor historical event scale | G7: date, hour, gate/zone, method, estimate | H7: Not started
A8: 1 | B8: Vendor, sponsor, and organizer budgets | C8: Organizer | D8: 2017–2019 | E8: CSV/PDF | F8: Map event money flows | G8: category, local/nonlocal, amount | H8: Not started
A9: 2 | B9: Parking counts, traffic plans, transit operations | C9: Transportation / AC Transit | D9: 2017–2019 | E9: CSV/PDF | F9: Calibrate mobility model | G9: facility, time, capacity, occupancy, service | H9: Not started
A10: 2 | B10: Nearby sales indicators or anonymized tax aggregates | C10: Finance / economic development | D10: Comparison weekends | E10: Aggregated CSV | F10: Estimate net local effects | G10: district, sector, period, taxable sales | H10: Not started
A11: 2 | B11: Waste tonnage and cleanup records | C11: Public Works / operator | D11: 2017–2019 | E11: CSV/PDF | F11: Environmental impact | G11: stream, weight, cost, date | H11: Not started
A12: 3 | B12: Media reach and public sentiment | C12: Organizer / City | D12: 2017–2019 | E12: CSV/PDF | F12: Civic visibility and value | G12: channel, reach, geography, sentiment | H12: Not started
A13: Pilot | B13: Attendee intercept survey | C13: Independent survey team | D13: Future event | E13: Survey data | F13: Incrementality and spending | G13: ZIP, party size, trip purpose, spending, mode | H13: Design needed
A14: Pilot | B14: Resident comparison survey | C14: Independent survey team | D14: Before/after pilot | E14: Survey data | F14: Distribution and public value | G14: residency, use, support, burden, WTP optional | H14: Design needed

Sheet README
A1: Model Guide
A2: Version 1.0 — working prototype for a Berkeley Kite Festival / civic-event counterfactual assessment.
A4: Purpose
A5: This workbook compares a festival scenario with a no-event counterfactual across City finances, local economics, mobility, emissions, and public value. It is a decision model—not evidence that the event should or should not return.
A7: How to use
A8: 1. Select Conservative, Central, or High on Controls!B5. 2. Replace blue illustrative assumptions with observed Berkeley data. 3. Review Dashboard and component sheets. 4. Use Evidence Register and Data Requests to document gaps. 5. Rebuild the fixed Monte Carlo draws if uncertainty structures change materially.
A10: Interpretation
A11: Economic output is not City revenue. City fiscal impact is not total public value. Gross attendee spending is reduced by attribution, local capture, and displacement before multipliers are applied.
A13: Color conventions
A14: Blue text = editable input; green text = linked from another sheet; black = formula; gray = static label; orange = missing/review item; purple = scenario control; teal = key result.
A16: Model limitations
A17: All event-specific numerical assumptions in v1 are illustrative unless replaced and documented. The model does not yet include anonymized card transactions, mobile-location data, a full traffic microsimulation, habitat valuation, or a statistically representative resident survey.
... A20: Reconstruct 2017–2019 City and organizer accounts, then design a one-day pilot with an intercept survey, parking/traffic counts, waste measurement, and pre-specified adjustment procedures.
